eztable/__init__.py
eztable/aggregation.py
eztable/columns.py
eztable/exceptions.py
eztable/index.py
eztable/row.py
eztable/table.py
eztable/table_literal.py
eztable/table_test_mixin.py
eztable-0.1.3.dist-info/DESCRIPTION.rst
eztable-0.1.3.dist-info/METADATA
eztable-0.1.3.dist-info/RECORD
eztable-0.1.3.dist-info/WHEEL
eztable-0.1.3.dist-info/metadata.json
eztable-0.1.3.dist-info/top_level.txt
eztable-0.1.3.dist-info/zip-safe
