Metadata-Version: 2.0
Name: eztable
Version: 0.1.3
Summary: Simple in-memory tables in pure Python.
Home-page: https://github.com/salimfadhley/eztable
Author: Salim Fadhley
Author-email: salimfadhley@gmail.com
License: MIT
Platform: UNKNOWN
Classifier: Development Status :: 5 - Production/Stable
Classifier: Environment :: Console
Classifier: Intended Audience :: Developers
Classifier: License :: OSI Approved :: MIT License
Classifier: Natural Language :: English
Classifier: Operating System :: OS Independent
Classifier: Programming Language :: Python :: 2.7
Classifier: Programming Language :: Python :: 3.4
Classifier: Programming Language :: Python :: 3.5
Classifier: Topic :: Software Development :: Testing
Classifier: Topic :: Utilities
Requires-Dist: bintrees (>=2.0.2)
Requires-Dist: six (>=1.9.0)
